{
  "decision": "OPEN",
  "event_status": "OK",
  "detections": [
    {
      "class_id": 2,
      "class": "car",
      "confidence": 0.5452,
      "confidence_percent": 54.52,
      "bbox": [
        2.59,
        30.66,
        620.96,
        457.09
      ],
      "allowed": true
    }
  ],
  "best_detection": {
    "class_id": 2,
    "class": "car",
    "confidence": 0.5452,
    "confidence_percent": 54.52,
    "bbox": [
      2.59,
      30.66,
      620.96,
      457.09
    ],
    "allowed": true
  },
  "best_allowed_detection": {
    "class_id": 2,
    "class": "car",
    "confidence": 0.5452,
    "confidence_percent": 54.52,
    "bbox": [
      2.59,
      30.66,
      620.96,
      457.09
    ],
    "allowed": true
  },
  "inference_ms": 391.35,
  "allowed_classes": [
    "bus",
    "car",
    "motorcycle",
    "truck"
  ],
  "confidence_threshold": 0.45,
  "img_size": 640,
  "request_id": "20260714_235437_653296",
  "timestamp": "2026-07-14T23:54:38",
  "direction": "EXIT",
  "sequence_id": null,
  "distance_cm": null,
  "object_detected": null,
  "model_path": "yolo26l.pt",
  "raw_image_path": "results/raw/EXIT_20260714_235437_653296.jpg",
  "annotated_image_path": "results/annotated/EXIT_20260714_235437_653296.jpg"
}